scikit_snowland-0.1.2.dist-info/DESCRIPTION.rst
scikit_snowland-0.1.2.dist-info/METADATA
scikit_snowland-0.1.2.dist-info/RECORD
scikit_snowland-0.1.2.dist-info/WHEEL
scikit_snowland-0.1.2.dist-info/metadata.json
scikit_snowland-0.1.2.dist-info/top_level.txt
snowland/__init__.py
snowland/image/__init__.py
snowland/image/api/__init__.py
snowland/image/api/img_to_cartoon.py
snowland/image/api/img_to_sketch.py
snowland/image/color/__init__.py
snowland/image/color/color.py
