Metadata-Version: 2.0
Name: scikit-snowland
Version: 0.1.2
Summary: scikit tool for image 
Home-page: https://gitee.com/hoops/snowland-img2cartoon
Author: A.Star
Author-email: astar@snowland.ltd
License: BSD License
Platform: all
Classifier: Development Status :: 4 - Beta
Classifier: Operating System :: OS Independent
Classifier: Intended Audience :: Developers
Classifier: License :: OSI Approved :: BSD License
Classifier: Programming Language :: Python
Classifier: Programming Language :: Python :: Implementation
Classifier: Programming Language :: Python :: 3
Classifier: Programming Language :: Python :: 3.4
Classifier: Programming Language :: Python :: 3.5
Classifier: Programming Language :: Python :: 3.6
Classifier: Topic :: Software Development :: Libraries
Requires-Dist: opencv-python (>=3.4.1.15)
Requires-Dist: numpy (>=1.0.0)
Requires-Dist: scikit-image (>=0.13)
Requires-Dist: matplotlib (>=2.1.2)
